{
  "total": 181,
  "limit": 250,
  "page": 0,
  "data": [
    {
      "page_id": "69acd058cd679a0086194851",
      "title": "ما هو الذكاء الاصطناعي؟ | Bright AI - دليلك الشامل",
      "num": 13,
      "discovered": 1772933208653,
      "info": "404",
      "target_url": "https://brightai.site/demo",
      "source_url": "https://brightai.site/what-is-ai/"
    },
    {
      "page_id": "69acd058cd679a0086194851",
      "title": "ما هو الذكاء الاصطناعي؟ | Bright AI - دليلك الشامل",
      "num": 15,
      "discovered": 1772933208653,
      "info": "404",
      "target_url": "https://brightai.site/job.MAISco",
      "source_url": "https://brightai.site/what-is-ai/"
    },
    {
      "page_id": "69acd058cd679a0086194892",
      "title": "أدوات AI مجانية للشركات | Bright AI",
      "num": 17,
      "discovered": 1772933208653,
      "info": "404",
      "target_url": "https://brightai.site/interview/pages/dashboard",
      "source_url": "https://brightai.site/tools/"
    },
    {
      "page_id": "69acd058cd679a0086194892",
      "title": "أدوات AI مجانية للشركات | Bright AI",
      "num": 15,
      "discovered": 1772933208653,
      "info": "404",
      "target_url": "https://brightai.site/interview/pages/supportAI",
      "source_url": "https://brightai.site/tools/"
    },
    {
      "page_id": "69acd058cd679a0086194892",
      "title": "أدوات AI مجانية للشركات | Bright AI",
      "num": 18,
      "discovered": 1772933208653,
      "info": "404",
      "target_url": "https://brightai.site/demo/ocr-demo",
      "source_url": "https://brightai.site/tools/"
    },
    {
      "page_id": "69acd058cd679a0086194892",
      "title": "أدوات AI مجانية للشركات | Bright AI",
      "num": 14,
      "discovered": 1772933208653,
      "info": "404",
      "target_url": "https://brightai.site/interview/pages/support-ai",
      "source_url": "https://brightai.site/tools/"
    },
    {
      "page_id": "69acd058cd679a0086194892",
      "title": "أدوات AI مجانية للشركات | Bright AI",
      "num": 13,
      "discovered": 1772933208653,
      "info": "404",
      "target_url": "https://brightai.site/interview",
      "source_url": "https://brightai.site/tools/"
    },
    {
      "page_id": "69acd058cd679a008619489a",
      "title": "الأتمتة الذكية وسير عمل AI | Bright AI السعودية",
      "num": 13,
      "discovered": 1772933208653,
      "info": "404",
      "target_url": "https://brightai.site/demo",
      "source_url": "https://brightai.site/smart-automation/"
    },
    {
      "page_id": "69acd058cd679a008619489a",
      "title": "الأتمتة الذكية وسير عمل AI | Bright AI السعودية",
      "num": 12,
      "discovered": 1772933208653,
      "info": "404",
      "target_url": "https://brightai.site/interview",
      "source_url": "https://brightai.site/smart-automation/"
    },
    {
      "page_id": "69acd058cd679a008619484f",
      "title": "خدمات AI المؤسسية للشركات | Bright AI",
      "num": 13,
      "discovered": 1772933208653,
      "info": "404",
      "target_url": "https://brightai.site/interview",
      "source_url": "https://brightai.site/services/"
    },
    {
      "page_id": "69acd058cd679a008619488b",
      "title": "تعلم الآلة للأعمال | Bright AI",
      "num": 14,
      "discovered": 1772933208653,
      "info": "404",
      "target_url": "https://brightai.site/interview",
      "source_url": "https://brightai.site/machine-learning/"
    },
    {
      "page_id": "69acd058cd679a008619484b",
      "title": "حلول الذكاء الاصطناعي الطبية المتقدمة | Bright AI السعودية",
      "num": 13,
      "discovered": 1772933208653,
      "info": "404",
      "target_url": "https://brightai.site/job.MAISco",
      "source_url": "https://brightai.site/health/"
    },
    {
      "page_id": "69acd058cd679a00861948c1",
      "title": "نماذج الذكاء الاصطناعي | Bright AI - جرب أدواتنا مجاناً",
      "num": 12,
      "discovered": 1772933208653,
      "info": "404",
      "target_url": "https://brightai.site/interview/pages/support-ai",
      "source_url": "https://brightai.site/frontend/pages/try/"
    },
    {
      "page_id": "69acd058cd679a00861948c1",
      "title": "نماذج الذكاء الاصطناعي | Bright AI - جرب أدواتنا مجاناً",
      "num": 15,
      "discovered": 1772933208653,
      "info": "404",
      "target_url": "https://brightai.site/try/data-analyzer",
      "source_url": "https://brightai.site/frontend/pages/try/"
    },
    {
      "page_id": "69acd058cd679a00861948c1",
      "title": "نماذج الذكاء الاصطناعي | Bright AI - جرب أدواتنا مجاناً",
      "num": 16,
      "discovered": 1772932025713,
      "info": "404",
      "target_url": "https://brightai.site/interview/pages/appointment",
      "source_url": "https://brightai.site/frontend/pages/try/"
    },
    {
      "page_id": "69acd058cd679a00861948c1",
      "title": "نماذج الذكاء الاصطناعي | Bright AI - جرب أدواتنا مجاناً",
      "num": 17,
      "discovered": 1772933208653,
      "info": "404",
      "target_url": "https://brightai.site/try/text-analysis",
      "source_url": "https://brightai.site/frontend/pages/try/"
    },
    {
      "page_id": "69acd058cd679a00861948c1",
      "title": "نماذج الذكاء الاصطناعي | Bright AI - جرب أدواتنا مجاناً",
      "num": 14,
      "discovered": 1772933208653,
      "info": "404",
      "target_url": "https://brightai.site/try/data-quality",
      "source_url": "https://brightai.site/frontend/pages/try/"
    },
    {
      "page_id": "69acd058cd679a00861948c1",
      "title": "نماذج الذكاء الاصطناعي | Bright AI - جرب أدواتنا مجاناً",
      "num": 13,
      "discovered": 1772933208653,
      "info": "404",
      "target_url": "https://brightai.site/job.MAISco",
      "source_url": "https://brightai.site/frontend/pages/try/"
    },
    {
      "page_id": "69acd058cd679a00861948c1",
      "title": "نماذج الذكاء الاصطناعي | Bright AI - جرب أدواتنا مجاناً",
      "num": 19,
      "discovered": 1772933208653,
      "info": "404",
      "target_url": "https://brightai.site/interview/pages/dashboard",
      "source_url": "https://brightai.site/frontend/pages/try/"
    },
    {
      "page_id": "69acd058cd679a00861948c1",
      "title": "نماذج الذكاء الاصطناعي | Bright AI - جرب أدواتنا مجاناً",
      "num": 11,
      "discovered": 1772933208653,
      "info": "404",
      "target_url": "https://brightai.site/demo",
      "source_url": "https://brightai.site/frontend/pages/try/"
    },
    {
      "page_id": "69acd058cd679a00861948be",
      "title": "نظام الأرشيف الطبي الذكي للمستشفيات في السعودية | تجربة",
      "num": 17,
      "discovered": 1772933208653,
      "info": "404",
      "target_url": "https://brightai.site/job.MAISco",
      "source_url": "https://brightai.site/frontend/pages/smart-medical-archive/"
    },
    {
      "page_id": "69acd058cd679a00861948be",
      "title": "نظام الأرشيف الطبي الذكي للمستشفيات في السعودية | تجربة",
      "num": 16,
      "discovered": 1772933208653,
      "info": "404",
      "target_url": "https://brightai.site/demo/ocr-demo",
      "source_url": "https://brightai.site/frontend/pages/smart-medical-archive/"
    },
    {
      "page_id": "69acd058cd679a0086194832",
      "title": "الذكاء الاصطناعي للصناعة السعودية | Bright AI",
      "num": 14,
      "discovered": 1772933208653,
      "info": "404",
      "target_url": "https://brightai.site/job.MAISco",
      "source_url": "https://brightai.site/frontend/pages/sectors/manufacturing.html"
    },
    {
      "page_id": "69acd058cd679a0086194879",
      "title": "الذكاء الاصطناعي للوجستيات في السعودية | Bright AI",
      "num": 14,
      "discovered": 1772933208653,
      "info": "404",
      "target_url": "https://brightai.site/job.MAISco",
      "source_url": "https://brightai.site/frontend/pages/sectors/logistics.html"
    },
    {
      "page_id": "69acd058cd679a0086194879",
      "title": "الذكاء الاصطناعي للوجستيات في السعودية | Bright AI",
      "num": 12,
      "discovered": 1772933208653,
      "info": "404",
      "target_url": "https://brightai.site/demo",
      "source_url": "https://brightai.site/frontend/pages/sectors/logistics.html"
    },
    {
      "page_id": "69acd058cd679a008619487a",
      "title": "الذكاء الاصطناعي للرعاية الصحية في السعودية | Bright AI",
      "num": 14,
      "discovered": 1772933208653,
      "info": "404",
      "target_url": "https://brightai.site/job.MAISco",
      "source_url": "https://brightai.site/frontend/pages/sectors/healthcare.html"
    },
    {
      "page_id": "69acd058cd679a0086194862",
      "title": "الذكاء الاصطناعي للقطاع المالي السعودي | Bright AI",
      "num": 13,
      "discovered": 1772933208653,
      "info": "404",
      "target_url": "https://brightai.site/job.MAISco",
      "source_url": "https://brightai.site/frontend/pages/sectors/finance.html"
    },
    {
      "page_id": "69acd058cd679a00861948c4",
      "title": "الذكاء الاصطناعي لقطاع الطاقة السعودي | Bright AI",
      "num": 13,
      "discovered": 1772933208653,
      "info": "404",
      "target_url": "https://brightai.site/job.MAISco",
      "source_url": "https://brightai.site/frontend/pages/sectors/energy.html"
    },
    {
      "page_id": "69acd058cd679a00861948a4",
      "title": "الذكاء الاصطناعي للتجارة الإلكترونية السعودية | Bright AI",
      "num": 13,
      "discovered": 1772933208653,
      "info": "404",
      "target_url": "https://brightai.site/job.MAISco",
      "source_url": "https://brightai.site/frontend/pages/sectors/ecommerce.html"
    },
    {
      "page_id": "69acd058cd679a0086194899",
      "title": "Bright AI | سياسة ملفات تعريف الارتباط",
      "num": 12,
      "discovered": 1772933208653,
      "info": "404",
      "target_url": "https://brightai.site/job.MAISco",
      "source_url": "https://brightai.site/frontend/pages/privacy-cookies/"
    },
    {
      "page_id": "69acd058cd679a008619484d",
      "title": "أسعار Bright AI | باقات مرنة للشركات السعودية",
      "num": 15,
      "discovered": 1772933208653,
      "info": "404",
      "target_url": "https://brightai.site/job.MAISco",
      "source_url": "https://brightai.site/frontend/pages/demo/pricing/"
    },
    {
      "page_id": "69acd058cd679a008619484d",
      "title": "أسعار Bright AI | باقات مرنة للشركات السعودية",
      "num": 13,
      "discovered": 1772933208653,
      "info": "404",
      "target_url": "https://brightai.site/demo",
      "source_url": "https://brightai.site/frontend/pages/demo/pricing/"
    },
    {
      "page_id": "69acd058cd679a00861948a6",
      "title": "كيف تغيّر الذكاء الاصطناعي مستقبل تحليل البيانات: الأدوات",
      "num": 12,
      "discovered": 1772933208653,
      "info": "404",
      "target_url": "https://brightai.site/job.MAISco",
      "source_url": "https://brightai.site/frontend/pages/blogger/مقال-تحليل.html"
    },
    {
      "page_id": "69acd058cd679a00861948a0",
      "title": "تعلم الآلة للأعمال في السعودية | Bright AI",
      "num": 13,
      "discovered": 1772933208653,
      "info": "404",
      "target_url": "https://brightai.site/job.MAISco",
      "source_url": "https://brightai.site/frontend/pages/blogger/تعلم-الآلة-و-الأعمال.html"
    },
    {
      "page_id": "69acd058cd679a0086194831",
      "title": "تحليل البيانات لاتخاذ القرار | Bright AI السعودية",
      "num": 11,
      "discovered": 1772932025713,
      "info": "404",
      "target_url": "https://brightai.site/blog/analysy",
      "source_url": "https://brightai.site/frontend/pages/blogger/تحليل-البيانات.html"
    },
    {
      "page_id": "69acd058cd679a0086194831",
      "title": "تحليل البيانات لاتخاذ القرار | Bright AI السعودية",
      "num": 13,
      "discovered": 1772933208653,
      "info": "404",
      "target_url": "https://brightai.site/job.MAISco",
      "source_url": "https://brightai.site/frontend/pages/blogger/تحليل-البيانات.html"
    },
    {
      "page_id": "69acd058cd679a008619483f",
      "title": "الذكاء الاصطناعي في التسويق | Bright AI السعودية",
      "num": 12,
      "discovered": 1772933208653,
      "info": "404",
      "target_url": "https://brightai.site/job.MAISco",
      "source_url": "https://brightai.site/frontend/pages/blogger/الذكاء-الاصطناعي-و-التسويق.html"
    },
    {
      "page_id": "69acd058cd679a0086194814",
      "title": "التعلم الآلي والرؤية الحاسوبية: مستقبل الذكاء الاصطناعي في",
      "num": 12,
      "discovered": 1772933208653,
      "info": "404",
      "target_url": "https://brightai.site/job.MAISco",
      "source_url": "https://brightai.site/frontend/pages/blogger/التعلم-الآلي-والرؤية-الحاسوبية-مستقبل-الذكاء-الاصطناعي-في-معالجة-اللغة-الطبيعية-والتعرف-على-الصور.html"
    },
    {
      "page_id": "69acd058cd679a00861948c5",
      "title": "التحول الرقمي وأتمتة العمليات: كيف يمكن للذكاء الاصطناعي أن",
      "num": 12,
      "discovered": 1772933208653,
      "info": "404",
      "target_url": "https://brightai.site/job.MAISco",
      "source_url": "https://brightai.site/frontend/pages/blogger/التحول-الرقمي-وأتمتة-العمليات-كيف-يمكن-للذكاء-الاصطناعي-أن-يقود-الابتكار.html"
    },
    {
      "page_id": "69acd058cd679a0086194809",
      "title": "الأتمتة المالية وأتمتة الموارد البشرية: حلول مستقبلية",
      "num": 11,
      "discovered": 1772933208653,
      "info": "404",
      "target_url": "https://brightai.site/job.MAISco",
      "source_url": "https://brightai.site/frontend/pages/blogger/الأتمتة-المالية-وأتمتة-الموارد-البشرية-حلول-مستقبلية-للشركات-الذكية.html"
    },
    {
      "page_id": "69acd058cd679a0086194812",
      "title": "الأتمتة الصناعية وأتمتة المهام المتكررة: - Ø§ÙØ£ØªÙ ØªØ© 2",
      "num": 11,
      "discovered": 1772933208653,
      "info": "404",
      "target_url": "https://brightai.site/job.MAISco",
      "source_url": "https://brightai.site/frontend/pages/blogger/الأتمتة-الصناعية-وأتمتة-المهام-المتكررة-كيفية-تحسين-الكفاءة-الإنتاجية.html"
    },
    {
      "page_id": "69acd058cd679a0086194853",
      "title": "أتمتة العمليات باستخدام الذكاء الاصطناعي: الطريق إلى تحسين",
      "num": 13,
      "discovered": 1772933208653,
      "info": "404",
      "target_url": "https://brightai.site/job.MAISco",
      "source_url": "https://brightai.site/frontend/pages/blogger/أتمتة-العمليات-باستخدام-الذكاء-الاصطناعي-الطريق-إلى-تحسين-الكفاءة-التشغيلية.html"
    },
    {
      "page_id": "69acd058cd679a0086194819",
      "title": "أتمتة الذكاء الاصطناعي: حلول مخصصة لتحليل المشاريع وتحسين",
      "num": 11,
      "discovered": 1772933208653,
      "info": "404",
      "target_url": "https://brightai.site/job.MAISco",
      "source_url": "https://brightai.site/frontend/pages/blogger/أتمتة-الذكاء-الاصطناعي-حلول-مخصصة-لتحليل-المشاريع-وتحسين-محركات-البحث-1.html"
    },
    {
      "page_id": "69acd058cd679a0086194876",
      "title": "حلول النقل واللوجستيات الذكية في السعودية | Bright AI",
      "num": 13,
      "discovered": 1772933208653,
      "info": "404",
      "target_url": "https://brightai.site/job.MAISco",
      "source_url": "https://brightai.site/frontend/pages/blogger/transport-logistics-solutions.html"
    },
    {
      "page_id": "69acd058cd679a0086194811",
      "title": "إدارة المخزون الذكية بالذكاء الاصطناعي | Bright AI",
      "num": 13,
      "discovered": 1772933208653,
      "info": "404",
      "target_url": "https://brightai.site/job.MAISco",
      "source_url": "https://brightai.site/frontend/pages/blogger/smart-inventory-management.html"
    },
    {
      "page_id": "69acd058cd679a0086194874",
      "title": "معالجة المستندات الذكية OCR في السعودية | Bright AI",
      "num": 13,
      "discovered": 1772933208653,
      "info": "404",
      "target_url": "https://brightai.site/job.MAISco",
      "source_url": "https://brightai.site/frontend/pages/blogger/smart-document-processing.html"
    },
    {
      "page_id": "69acd058cd679a008619483b",
      "title": "نظام CRM ذكي بالذكاء الاصطناعي في السعودية | Bright AI",
      "num": 14,
      "discovered": 1772933208653,
      "info": "404",
      "target_url": "https://brightai.site/job.MAISco",
      "source_url": "https://brightai.site/frontend/pages/blogger/smart-crm-system.html"
    },
    {
      "page_id": "69acd058cd679a008619482f",
      "title": "فوائد الأتمتة الذكية للشركات | Bright AI السعودية",
      "num": 12,
      "discovered": 1772933208653,
      "info": "404",
      "target_url": "https://brightai.site/job.MAISco",
      "source_url": "https://brightai.site/frontend/pages/blogger/smart-automation-benefits.html"
    },
    {
      "page_id": "69acd058cd679a0086194881",
      "title": "دراسة حالة شاملة: إدارة النفايات بالذكاء الاصطناعي في",
      "num": 11,
      "discovered": 1772933208653,
      "info": "404",
      "target_url": "https://brightai.site/job.MAISco",
      "source_url": "https://brightai.site/frontend/pages/blogger/saudi-waste-management-ai.html"
    },
    {
      "page_id": "69acd058cd679a0086194877",
      "title": "دراسة حالة شاملة: الذكاء الاصطناعي في السياحة السعودية |",
      "num": 12,
      "discovered": 1772933208653,
      "info": "404",
      "target_url": "https://brightai.site/job.MAISco",
      "source_url": "https://brightai.site/frontend/pages/blogger/saudi-tourism-ai-guide.html"
    },
    {
      "page_id": "69acd058cd679a008619489d",
      "title": "دراسة حالة شاملة: الذكاء الاصطناعي في الرياضة السعودية |",
      "num": 12,
      "discovered": 1772933208653,
      "info": "404",
      "target_url": "https://brightai.site/job.MAISco",
      "source_url": "https://brightai.site/frontend/pages/blogger/saudi-sports-analytics-ai.html"
    },
    {
      "page_id": "69acd058cd679a0086194840",
      "title": "دراسة حالة شاملة: الرياض تقلل الازدحام 30% | Bright AI",
      "num": 11,
      "discovered": 1772933208653,
      "info": "404",
      "target_url": "https://brightai.site/job.MAISco",
      "source_url": "https://brightai.site/frontend/pages/blogger/saudi-smart-city-traffic.html"
    },
    {
      "page_id": "69acd058cd679a008619482e",
      "title": "دراسة حالة شاملة: الذكاء الاصطناعي في الطاقة المتجددة",
      "num": 11,
      "discovered": 1772933208653,
      "info": "404",
      "target_url": "https://brightai.site/job.MAISco",
      "source_url": "https://brightai.site/frontend/pages/blogger/saudi-renewable-energy-ai.html"
    },
    {
      "page_id": "69acd058cd679a0086194847",
      "title": "دراسة حالة شاملة: الذكاء الاصطناعي في العقارات السعودية |",
      "num": 12,
      "discovered": 1772933208653,
      "info": "404",
      "target_url": "https://brightai.site/job.MAISco",
      "source_url": "https://brightai.site/frontend/pages/blogger/saudi-real-estate-ai-valuation.html"
    },
    {
      "page_id": "69acd058cd679a008619486a",
      "title": "دراسة حالة شاملة: الذكاء الاصطناعي في البتروكيماويات",
      "num": 12,
      "discovered": 1772933208653,
      "info": "404",
      "target_url": "https://brightai.site/job.MAISco",
      "source_url": "https://brightai.site/frontend/pages/blogger/saudi-petrochemical-ai-safety.html"
    },
    {
      "page_id": "69acd058cd679a0086194845",
      "title": "دراسة حالة شاملة: الذكاء الاصطناعي في التعدين السعودي | كنز",
      "num": 12,
      "discovered": 1772933208653,
      "info": "404",
      "target_url": "https://brightai.site/job.MAISco",
      "source_url": "https://brightai.site/frontend/pages/blogger/saudi-mining-ai-exploration.html"
    },
    {
      "page_id": "69acd058cd679a00861948ad",
      "title": "دراسة حالة شاملة: الذكاء الاصطناعي في الصناعة السعودية |",
      "num": 13,
      "discovered": 1772933208653,
      "info": "404",
      "target_url": "https://brightai.site/job.MAISco",
      "source_url": "https://brightai.site/frontend/pages/blogger/saudi-manufacturing-predictive-maintenance.html"
    },
    {
      "page_id": "69acd058cd679a00861948ad",
      "title": "دراسة حالة شاملة: الذكاء الاصطناعي في الصناعة السعودية |",
      "num": 11,
      "discovered": 1772933208653,
      "info": "404",
      "target_url": "https://brightai.site/demo",
      "source_url": "https://brightai.site/frontend/pages/blogger/saudi-manufacturing-predictive-maintenance.html"
    },
    {
      "page_id": "69acd058cd679a00861948a5",
      "title": "دراسة حالة شاملة: الذكاء الاصطناعي في اللوجستيات السعودية |",
      "num": 12,
      "discovered": 1772933208653,
      "info": "404",
      "target_url": "https://brightai.site/job.MAISco",
      "source_url": "https://brightai.site/frontend/pages/blogger/saudi-logistics-route-optimization.html"
    },
    {
      "page_id": "69acd058cd679a00861948bc",
      "title": "دراسة حالة شاملة: الذكاء الاصطناعي في التأمين السعودي | كشف",
      "num": 12,
      "discovered": 1772933208653,
      "info": "404",
      "target_url": "https://brightai.site/job.MAISco",
      "source_url": "https://brightai.site/frontend/pages/blogger/saudi-insurance-claims-ai.html"
    },
    {
      "page_id": "69acd058cd679a0086194855",
      "title": "دراسة حالة: مجموعة فنادق سعودية | زيادة الإشغال 20%",
      "num": 12,
      "discovered": 1772933208653,
      "info": "404",
      "target_url": "https://brightai.site/job.MAISco",
      "source_url": "https://brightai.site/frontend/pages/blogger/saudi-hospitality-dynamic-pricing.html"
    },
    {
      "page_id": "69acd058cd679a0086194891",
      "title": "دراسة حالة: مصنع سعودي | رفع الإنتاجية 30% بتحليلات الذكاء",
      "num": 11,
      "discovered": 1772933208653,
      "info": "404",
      "target_url": "https://brightai.site/demo",
      "source_url": "https://brightai.site/frontend/pages/blogger/saudi-factory-ai-productivity.html"
    },
    {
      "page_id": "69acd058cd679a0086194891",
      "title": "دراسة حالة: مصنع سعودي | رفع الإنتاجية 30% بتحليلات الذكاء",
      "num": 13,
      "discovered": 1772933208653,
      "info": "404",
      "target_url": "https://brightai.site/job.MAISco",
      "source_url": "https://brightai.site/frontend/pages/blogger/saudi-factory-ai-productivity.html"
    },
    {
      "page_id": "69acd058cd679a0086194882",
      "title": "دراسة حالة: شركة طاقة سعودية | توفير 40 مليون ريال سنوياً",
      "num": 11,
      "discovered": 1772933208653,
      "info": "404",
      "target_url": "https://brightai.site/demo",
      "source_url": "https://brightai.site/frontend/pages/blogger/saudi-energy-predictive-maintenance.html"
    },
    {
      "page_id": "69acd058cd679a0086194882",
      "title": "دراسة حالة: شركة طاقة سعودية | توفير 40 مليون ريال سنوياً",
      "num": 13,
      "discovered": 1772933208653,
      "info": "404",
      "target_url": "https://brightai.site/job.MAISco",
      "source_url": "https://brightai.site/frontend/pages/blogger/saudi-energy-predictive-maintenance.html"
    },
    {
      "page_id": "69acd058cd679a0086194849",
      "title": "دراسة حالة: منصة تعليمية سعودية | تخصيص مسارات التعلم لـ",
      "num": 12,
      "discovered": 1772933208653,
      "info": "404",
      "target_url": "https://brightai.site/job.MAISco",
      "source_url": "https://brightai.site/frontend/pages/blogger/saudi-edtech-personalized-learning.html"
    },
    {
      "page_id": "69acd058cd679a00861948c2",
      "title": "دراسة حالة شاملة: الذكاء الاصطناعي في التجارة الإلكترونية",
      "num": 12,
      "discovered": 1772933208653,
      "info": "404",
      "target_url": "https://brightai.site/job.MAISco",
      "source_url": "https://brightai.site/frontend/pages/blogger/saudi-ecommerce-ai-growth.html"
    },
    {
      "page_id": "69acd058cd679a008619481a",
      "title": "دراسة حالة شاملة: الذكاء الاصطناعي في جودة التمور السعودية",
      "num": 12,
      "discovered": 1772933208653,
      "info": "404",
      "target_url": "https://brightai.site/job.MAISco",
      "source_url": "https://brightai.site/frontend/pages/blogger/saudi-dates-quality-ai.html"
    },
    {
      "page_id": "69acd058cd679a008619487f",
      "title": "دراسة حالة: بنك سعودي | كشف 95% من محاولات الاحتيال بالذكاء",
      "num": 13,
      "discovered": 1772933208653,
      "info": "404",
      "target_url": "https://brightai.site/job.MAISco",
      "source_url": "https://brightai.site/frontend/pages/blogger/saudi-bank-fraud-detection.html"
    },
    {
      "page_id": "69acd058cd679a008619487f",
      "title": "دراسة حالة: بنك سعودي | كشف 95% من محاولات الاحتيال بالذكاء",
      "num": 11,
      "discovered": 1772933208653,
      "info": "404",
      "target_url": "https://brightai.site/demo",
      "source_url": "https://brightai.site/frontend/pages/blogger/saudi-bank-fraud-detection.html"
    },
    {
      "page_id": "69acd058cd679a008619485a",
      "title": "دراسة حالة شاملة: الزراعة الذكية في السعودية | توفير المياه",
      "num": 12,
      "discovered": 1772933208653,
      "info": "404",
      "target_url": "https://brightai.site/job.MAISco",
      "source_url": "https://brightai.site/frontend/pages/blogger/saudi-agritech-smart-farming.html"
    },
    {
      "page_id": "69acd058cd679a0086194810",
      "title": "دراسة حالة: كيف خفّضت بلدية الرياض وقت التراخيص 70% بالذكاء",
      "num": 11,
      "discovered": 1772933208653,
      "info": "404",
      "target_url": "https://brightai.site/job.MAISco",
      "source_url": "https://brightai.site/frontend/pages/blogger/riyadh-municipality-ai-license.html"
    },
    {
      "page_id": "69acd058cd679a0086194898",
      "title": "كيف يُحسّن الذكاء الاصطناعي كفاءة خطوط الإنتاج؟ | Bright AI",
      "num": 11,
      "discovered": 1772933208653,
      "info": "404",
      "target_url": "https://brightai.site/demo",
      "source_url": "https://brightai.site/frontend/pages/blogger/production-line.html"
    },
    {
      "page_id": "69acd058cd679a0086194898",
      "title": "كيف يُحسّن الذكاء الاصطناعي كفاءة خطوط الإنتاج؟ | Bright AI",
      "num": 13,
      "discovered": 1772933208653,
      "info": "404",
      "target_url": "https://brightai.site/job.MAISco",
      "source_url": "https://brightai.site/frontend/pages/blogger/production-line.html"
    },
    {
      "page_id": "69acd058cd679a008619481c",
      "title": "أتمتة العمليات: تحويل المهام الروتينية إلى عمليات مؤتمتة",
      "num": 13,
      "discovered": 1772933208653,
      "info": "404",
      "target_url": "https://brightai.site/job.MAISco",
      "source_url": "https://brightai.site/frontend/pages/blogger/process-automation.html"
    },
    {
      "page_id": "69acd058cd679a008619481c",
      "title": "أتمتة العمليات: تحويل المهام الروتينية إلى عمليات مؤتمتة",
      "num": 12,
      "discovered": 1772932025713,
      "info": "404",
      "target_url": "https://brightai.site/blog/استشارات-الذكاء-الاصطناعي-كيف-تسهم-في-تحقيق-التحول-الرقمي-للشركات",
      "source_url": "https://brightai.site/frontend/pages/blogger/process-automation.html"
    },
    {
      "page_id": "69acd058cd679a008619487c",
      "title": "دراسة حالة: مجموعة صحية خاصة | تقليل أوقات الانتظار بنسبة",
      "num": 12,
      "discovered": 1772933208653,
      "info": "404",
      "target_url": "https://brightai.site/job.MAISco",
      "source_url": "https://brightai.site/frontend/pages/blogger/private-hospital-scheduling-optimization.html"
    },
    {
      "page_id": "69acd058cd679a0086194870",
      "title": "الامتثال لمعايير الأمن السيبراني (NCA) في السعودية | الدليل",
      "num": 12,
      "discovered": 1772933208653,
      "info": "404",
      "target_url": "https://brightai.site/job.MAISco",
      "source_url": "https://brightai.site/frontend/pages/blogger/nca-compliance.html"
    },
    {
      "page_id": "69acd058cd679a00861948a3",
      "title": "دراسة حالة: جامعة الملك سعود | منصة تعلم تكيفي ترفع معدلات",
      "num": 12,
      "discovered": 1772933208653,
      "info": "404",
      "target_url": "https://brightai.site/job.MAISco",
      "source_url": "https://brightai.site/frontend/pages/blogger/ksu-adaptive-learning.html"
    },
    {
      "page_id": "69acd058cd679a0086194884",
      "title": "دراسة حالة: مستشفى الملك فيصل التخصصي | الذكاء الاصطناعي",
      "num": 11,
      "discovered": 1772933208653,
      "info": "404",
      "target_url": "https://brightai.site/job.MAISco",
      "source_url": "https://brightai.site/frontend/pages/blogger/kfshrc-breast-cancer-ai.html"
    },
    {
      "page_id": "69acd058cd679a00861948b8",
      "title": "دليل شامل لتحليل البيانات الذكي: تحويل المعلومات إلى قرارات",
      "num": 15,
      "discovered": 1772932025713,
      "info": "404",
      "target_url": "https://brightai.site/blog/astr.doc",
      "source_url": "https://brightai.site/frontend/pages/blogger/intelligent-data-analysis.html"
    },
    {
      "page_id": "69acd058cd679a00861948b8",
      "title": "دليل شامل لتحليل البيانات الذكي: تحويل المعلومات إلى قرارات",
      "num": 13,
      "discovered": 1772932025713,
      "info": "404",
      "target_url": "https://brightai.site/blog/استشارات-الذكاء-الاصطناعي-كيف-تسهم-في-تحقيق-التحول-الرقمي-للشركات",
      "source_url": "https://brightai.site/frontend/pages/blogger/intelligent-data-analysis.html"
    },
    {
      "page_id": "69acd058cd679a00861948b8",
      "title": "دليل شامل لتحليل البيانات الذكي: تحويل المعلومات إلى قرارات",
      "num": 14,
      "discovered": 1772933208653,
      "info": "404",
      "target_url": "https://brightai.site/job.MAISco",
      "source_url": "https://brightai.site/frontend/pages/blogger/intelligent-data-analysis.html"
    },
    {
      "page_id": "69acd058cd679a00861948b8",
      "title": "دليل شامل لتحليل البيانات الذكي: تحويل المعلومات إلى قرارات",
      "num": 11,
      "discovered": 1772932025713,
      "info": "404",
      "target_url": "https://brightai.site/blog/analysy",
      "source_url": "https://brightai.site/frontend/pages/blogger/intelligent-data-analysis.html"
    },
    {
      "page_id": "69acd058cd679a0086194860",
      "title": "الأتمتة الذكية للموارد البشرية: كيف وفّرت شركة | Bright AI",
      "num": 5,
      "discovered": 1772933208653,
      "info": "404",
      "target_url": "https://brightai.site/interview",
      "source_url": "https://brightai.site/frontend/pages/blogger/hr-automation-case-study.html"
    },
    {
      "page_id": "69acd058cd679a00861948b6",
      "title": "التحليل الذكي للقطاع المالي | Bright AI السعودية",
      "num": 12,
      "discovered": 1772933208653,
      "info": "404",
      "target_url": "https://brightai.site/demo",
      "source_url": "https://brightai.site/frontend/pages/blogger/future-of-intelligent-data-analysis-finance-sector.html"
    },
    {
      "page_id": "69acd058cd679a00861948b6",
      "title": "التحليل الذكي للقطاع المالي | Bright AI السعودية",
      "num": 13,
      "discovered": 1772933208653,
      "info": "404",
      "target_url": "https://brightai.site/job.MAISco",
      "source_url": "https://brightai.site/frontend/pages/blogger/future-of-intelligent-data-analysis-finance-sector.html"
    },
    {
      "page_id": "69acd058cd679a0086194861",
      "title": "تطبيقات الصحة الرقمية والأرشفة الطبية الذكية في | Bright AI",
      "num": 13,
      "discovered": 1772933208653,
      "info": "404",
      "target_url": "https://brightai.site/job.MAISco",
      "source_url": "https://brightai.site/frontend/pages/blogger/digital-health-smart-archive.html"
    },
    {
      "page_id": "69acd058cd679a0086194830",
      "title": "الخدمات المصرفية الرقمية في السعودية | Bright AI",
      "num": 14,
      "discovered": 1772933208653,
      "info": "404",
      "target_url": "https://brightai.site/job.MAISco",
      "source_url": "https://brightai.site/frontend/pages/blogger/digital-banking-saudi.html"
    },
    {
      "page_id": "69acd058cd679a0086194830",
      "title": "الخدمات المصرفية الرقمية في السعودية | Bright AI",
      "num": 12,
      "discovered": 1772933208653,
      "info": "404",
      "target_url": "https://brightai.site/demo",
      "source_url": "https://brightai.site/frontend/pages/blogger/digital-banking-saudi.html"
    },
    {
      "page_id": "69acd058cd679a0086194852",
      "title": "دراسة حالة: وزارة التجارة | شات بوت ذكي يخدم 50,000 تاجر",
      "num": 12,
      "discovered": 1772933208653,
      "info": "404",
      "target_url": "https://brightai.site/job.MAISco",
      "source_url": "https://brightai.site/frontend/pages/blogger/commerce-ministry-chatbot.html"
    },
    {
      "page_id": "69acd058cd679a008619485d",
      "title": "كيف تختار شركة الذكاء الاصطناعي المناسبة في | Bright AI",
      "num": 5,
      "discovered": 1772933208653,
      "info": "404",
      "target_url": "https://brightai.site/interview",
      "source_url": "https://brightai.site/frontend/pages/blogger/choose-ai-company-saudi.html"
    },
    {
      "page_id": "69acd058cd679a008619481f",
      "title": "دراسة حالة: كيف تستخدم الشركات السعودية وكلاء الذكاء",
      "num": 13,
      "discovered": 1772933208653,
      "info": "404",
      "target_url": "https://brightai.site/job.MAISco",
      "source_url": "https://brightai.site/frontend/pages/blogger/case-study-saudi-companies-ai-agents-customer-service.html"
    },
    {
      "page_id": "69acd058cd679a0086194848",
      "title": "ذكاء الأعمال BI في السعودية | Bright AI",
      "num": 12,
      "discovered": 1772932025713,
      "info": "404",
      "target_url": "https://brightai.site/blog/analysy",
      "source_url": "https://brightai.site/frontend/pages/blogger/business-intelligence-saudi.html"
    },
    {
      "page_id": "69acd058cd679a0086194848",
      "title": "ذكاء الأعمال BI في السعودية | Bright AI",
      "num": 14,
      "discovered": 1772933208653,
      "info": "404",
      "target_url": "https://brightai.site/job.MAISco",
      "source_url": "https://brightai.site/frontend/pages/blogger/business-intelligence-saudi.html"
    },
    {
      "page_id": "69acd058cd679a0086194820",
      "title": "ذكاء الاعمال: قوة تحليل البيانات لتحسين الأداء | Bright AI",
      "num": 12,
      "discovered": 1772933208653,
      "info": "404",
      "target_url": "https://brightai.site/job.MAISco",
      "source_url": "https://brightai.site/frontend/pages/blogger/business-intelligence-data-analysis.html"
    },
    {
      "page_id": "69acd058cd679a00861948bb",
      "title": "تحليل البيانات الضخمة للأعمال | Bright AI السعودية",
      "num": 10,
      "discovered": 1772932025713,
      "info": "404",
      "target_url": "https://brightai.site/blog/analysy",
      "source_url": "https://brightai.site/frontend/pages/blogger/big-data-analysis.html"
    },
    {
      "page_id": "69acd058cd679a00861948bb",
      "title": "تحليل البيانات الضخمة للأعمال | Bright AI السعودية",
      "num": 12,
      "discovered": 1772933208653,
      "info": "404",
      "target_url": "https://brightai.site/job.MAISco",
      "source_url": "https://brightai.site/frontend/pages/blogger/big-data-analysis.html"
    },
    {
      "page_id": "69acd058cd679a00861948b7",
      "title": "أتمتة العمليات الذكية | حلول Bright AI المتكاملة لتحويل",
      "num": 12,
      "discovered": 1772933208653,
      "info": "404",
      "target_url": "https://brightai.site/job.MAISco",
      "source_url": "https://brightai.site/frontend/pages/blogger/atou.doc.html"
    },
    {
      "page_id": "69acd058cd679a008619489e",
      "title": "كيف يمكن للذكاء الاصطناعي تحسين أداء الشركات | Bright AI",
      "num": 11,
      "discovered": 1772933208653,
      "info": "404",
      "target_url": "https://brightai.site/job.MAISco",
      "source_url": "https://brightai.site/frontend/pages/blogger/ai.html"
    },
    {
      "page_id": "69acd058cd679a008619484c",
      "title": "كيف تُحدث حلول الذكاء الاصطناعي المبتكرة تحولًا في الأعمال",
      "num": 13,
      "discovered": 1772933208653,
      "info": "404",
      "target_url": "https://brightai.site/job.MAISco",
      "source_url": "https://brightai.site/frontend/pages/blogger/ai-transformation.html"
    },
    {
      "page_id": "69acd058cd679a0086194842",
      "title": "5 طرق لتعزيز الابتكار من خلال الذكاء الاصطناعي في السعودية | Bright AI",
      "num": 11,
      "discovered": 1772933208653,
      "info": "404",
      "target_url": "https://brightai.site/job.MAISco",
      "source_url": "https://brightai.site/frontend/pages/blogger/ai-innovation-saudi-arabia.html"
    },
    {
      "page_id": "69acd058cd679a008619487e",
      "title": "الذكاء الاصطناعي في القطاع الصحي السعودي: تشخيص | Bright AI",
      "num": 11,
      "discovered": 1772933208653,
      "info": "404",
      "target_url": "https://brightai.site/job.MAISco",
      "source_url": "https://brightai.site/frontend/pages/blogger/ai-healthcare-saudi.html"
    },
    {
      "page_id": "69acd058cd679a008619480f",
      "title": "تأثير الذكاء الاصطناعي التوليدي على صناعة المحتوى في",
      "num": 12,
      "discovered": 1772933208653,
      "info": "404",
      "target_url": "https://brightai.site/job.MAISco",
      "source_url": "https://brightai.site/frontend/pages/blogger/ai-generative-content-industry-saudi-arabia.html"
    },
    {
      "page_id": "69acd058cd679a0086194866",
      "title": "الذكاء الاصطناعي للقطاع المالي السعودي | مصرفية أذكى",
      "num": 10,
      "discovered": 1772933208653,
      "info": "404",
      "target_url": "https://brightai.site/demo",
      "source_url": "https://brightai.site/frontend/pages/blogger/ai-finance-saudi.html"
    },
    {
      "page_id": "69acd058cd679a0086194866",
      "title": "الذكاء الاصطناعي للقطاع المالي السعودي | مصرفية أذكى",
      "num": 12,
      "discovered": 1772933208653,
      "info": "404",
      "target_url": "https://brightai.site/job.MAISco",
      "source_url": "https://brightai.site/frontend/pages/blogger/ai-finance-saudi.html"
    },
    {
      "page_id": "69acd058cd679a0086194895",
      "title": "الذكاء الاصطناعي في قطاع الطاقة السعودي | كفاءة أعلى",
      "num": 11,
      "discovered": 1772933208653,
      "info": "404",
      "target_url": "https://brightai.site/job.MAISco",
      "source_url": "https://brightai.site/frontend/pages/blogger/ai-energy-saudi.html"
    },
    {
      "page_id": "69acd058cd679a0086194813",
      "title": "وكيل الذكاء الاصطناعي للشركات | Bright AI السعودية",
      "num": 12,
      "discovered": 1772933208653,
      "info": "404",
      "target_url": "https://brightai.site/job.MAISco",
      "source_url": "https://brightai.site/frontend/pages/blogger/ai-agent.html"
    },
    {
      "page_id": "69acd058cd679a0086194890",
      "title": "الذكاء الاصطناعي التوليدي: ثورة في عالم الإبداع | Bright AI",
      "num": 12,
      "discovered": 1772933208653,
      "info": "404",
      "target_url": "https://brightai.site/job.MAISco",
      "source_url": "https://brightai.site/frontend/pages/blogger/Generative-artificial-intelligence.html"
    },
    {
      "page_id": "69acd058cd679a00861948c0",
      "title": "Power BI للشركات السعودية: دليل البداية الشامل | Bright AI",
      "num": 12,
      "discovered": 1772933208653,
      "info": "404",
      "target_url": "https://brightai.site/job.MAISco",
      "source_url": "https://brightai.site/frontend/pages/blog/data-analytics/power-bi-saudi-guide.html"
    },
    {
      "page_id": "69acd058cd679a00861948a8",
      "title": "كيف تبني لوحة معلومات KPIs لمنشأتك خطوة بخطوة | Bright AI",
      "num": 11,
      "discovered": 1772933208653,
      "info": "404",
      "target_url": "https://brightai.site/job.MAISco",
      "source_url": "https://brightai.site/frontend/pages/blog/data-analytics/kpi-dashboard-guide.html"
    },
    {
      "page_id": "69acd058cd679a00861948a2",
      "title": "سير عمل الذكاء الاصطناعي للشركات السعودية | Bright AI",
      "num": 13,
      "discovered": 1772933208653,
      "info": "404",
      "target_url": "https://brightai.site/demo",
      "source_url": "https://brightai.site/frontend/pages/ai-workflows/"
    },
    {
      "page_id": "69acd058cd679a00861948a2",
      "title": "سير عمل الذكاء الاصطناعي للشركات السعودية | Bright AI",
      "num": 15,
      "discovered": 1772933208653,
      "info": "404",
      "target_url": "https://brightai.site/job.MAISco",
      "source_url": "https://brightai.site/frontend/pages/ai-workflows/"
    },
    {
      "page_id": "69acd058cd679a00861948ab",
      "title": "المنصة التعليمية الذكية | Bright AI",
      "num": 14,
      "discovered": 1772933208653,
      "info": "404",
      "target_url": "https://brightai.site/job.MAISco",
      "source_url": "https://brightai.site/frontend/pages/ai-scolecs/"
    },
    {
      "page_id": "69acd058cd679a0086194871",
      "title": "BrightSupport - روبوت خدمة العملاء الذكي",
      "num": 12,
      "discovered": 1772933208653,
      "info": "404",
      "target_url": "https://brightai.site/job.MAISco",
      "source_url": "https://brightai.site/frontend/pages/ai-bots/BrightSupport/"
    },
    {
      "page_id": "69acd058cd679a00861948ba",
      "title": "BrightSales | روبوت المبيعات الذكي في السعودية",
      "num": 12,
      "discovered": 1772933208653,
      "info": "404",
      "target_url": "https://brightai.site/job.MAISco",
      "source_url": "https://brightai.site/frontend/pages/ai-bots/BrightSales/"
    },
    {
      "page_id": "69acd058cd679a00861948b4",
      "title": "BrightRecruiter | روبوت التوظيف الذكي في السعودية",
      "num": 12,
      "discovered": 1772933208653,
      "info": "404",
      "target_url": "https://brightai.site/job.MAISco",
      "source_url": "https://brightai.site/frontend/pages/ai-bots/BrightRecruiter/"
    },
    {
      "page_id": "69acd058cd679a008619484e",
      "title": "BrightProject | روبوت إدارة المشاريع الذكي في السعودية",
      "num": 12,
      "discovered": 1772933208653,
      "info": "404",
      "target_url": "https://brightai.site/job.MAISco",
      "source_url": "https://brightai.site/frontend/pages/ai-bots/BrightProject/"
    },
    {
      "page_id": "69acd058cd679a008619481d",
      "title": "BrightMath | مساعد الرياضيات الذكي في السعودية",
      "num": 13,
      "discovered": 1772933208653,
      "info": "404",
      "target_url": "https://brightai.site/job.MAISco",
      "source_url": "https://brightai.site/frontend/pages/ai-bots/BrightMath/"
    },
    {
      "page_id": "69acd058cd679a0086194897",
      "title": "Terms & Conditions | Bright AI - The Fine Print",
      "num": 10,
      "discovered": 1772933208653,
      "info": "404",
      "target_url": "https://brightai.site/interview",
      "source_url": "https://brightai.site/docs/terms-and-conditions-en"
    },
    {
      "page_id": "69acd058cd679a0086194818",
      "title": "الشروط والأحكام | Bright AI - شروط استخدام خدماتنا",
      "num": 10,
      "discovered": 1772933208653,
      "info": "404",
      "target_url": "https://brightai.site/interview",
      "source_url": "https://brightai.site/docs/terms-and-conditions"
    },
    {
      "page_id": "69acd058cd679a0086194836",
      "title": "Supply Chain Management | Bright AI - Plan Ahead",
      "num": 10,
      "discovered": 1772933208653,
      "info": "404",
      "target_url": "https://brightai.site/interview",
      "source_url": "https://brightai.site/docs/solutions-supply-chain-en"
    },
    {
      "page_id": "69acd058cd679a0086194894",
      "title": "إدارة سلسلة الإمداد (SCM) | Bright AI - تخطيط الطلب والمخزون",
      "num": 10,
      "discovered": 1772933208653,
      "info": "404",
      "target_url": "https://brightai.site/interview",
      "source_url": "https://brightai.site/docs/solutions-supply-chain"
    },
    {
      "page_id": "69acd058cd679a0086194844",
      "title": "Retail & E-commerce | Bright AI - Sell Smarter",
      "num": 10,
      "discovered": 1772933208653,
      "info": "404",
      "target_url": "https://brightai.site/interview",
      "source_url": "https://brightai.site/docs/solutions-retail-en"
    },
    {
      "page_id": "69acd058cd679a00861948a7",
      "title": "حلول التجزئة والتجارة الإلكترونية | Bright AI - بيع بذكاء",
      "num": 10,
      "discovered": 1772933208653,
      "info": "404",
      "target_url": "https://brightai.site/interview",
      "source_url": "https://brightai.site/docs/solutions-retail"
    },
    {
      "page_id": "69acd058cd679a0086194864",
      "title": "Intelligent Document Processing (OCR) | Bright AI",
      "num": 10,
      "discovered": 1772933208653,
      "info": "404",
      "target_url": "https://brightai.site/interview",
      "source_url": "https://brightai.site/docs/solutions-ocr-en"
    },
    {
      "page_id": "69acd058cd679a008619483c",
      "title": "معالجة المستندات الذكية (OCR) | Bright AI",
      "num": 10,
      "discovered": 1772933208653,
      "info": "404",
      "target_url": "https://brightai.site/interview",
      "source_url": "https://brightai.site/docs/solutions-ocr"
    },
    {
      "page_id": "69acd058cd679a008619483c",
      "title": "معالجة المستندات الذكية (OCR) | Bright AI",
      "num": 12,
      "discovered": 1772933208653,
      "info": "404",
      "target_url": "https://brightai.site/demo/ocr-demo",
      "source_url": "https://brightai.site/docs/solutions-ocr"
    },
    {
      "page_id": "69acd058cd679a0086194878",
      "title": "Logistics & Fleet | Bright AI السعودية",
      "num": 10,
      "discovered": 1772933208653,
      "info": "404",
      "target_url": "https://brightai.site/interview",
      "source_url": "https://brightai.site/docs/solutions-logistics-en"
    },
    {
      "page_id": "69acd058cd679a0086194888",
      "title": "حلول اللوجستيات والنقل الذكي | Bright AI",
      "num": 10,
      "discovered": 1772933208653,
      "info": "404",
      "target_url": "https://brightai.site/interview",
      "source_url": "https://brightai.site/docs/solutions-logistics"
    },
    {
      "page_id": "69acd058cd679a00861948b3",
      "title": "Smart Hiring | Bright AI - Recruitment on Autopilot",
      "num": 10,
      "discovered": 1772933208653,
      "info": "404",
      "target_url": "https://brightai.site/interview",
      "source_url": "https://brightai.site/docs/solutions-interview-en"
    },
    {
      "page_id": "69acd058cd679a00861948c3",
      "title": "حلول الموارد البشرية والتوظيف | Bright AI - وظف بذكاء",
      "num": 10,
      "discovered": 1772933208653,
      "info": "404",
      "target_url": "https://brightai.site/interview",
      "source_url": "https://brightai.site/docs/solutions-interview"
    },
    {
      "page_id": "69acd058cd679a0086194841",
      "title": "HR Management (HRMS) | Bright AI - Payroll & Automation",
      "num": 10,
      "discovered": 1772933208653,
      "info": "404",
      "target_url": "https://brightai.site/interview",
      "source_url": "https://brightai.site/docs/solutions-hr-en"
    },
    {
      "page_id": "69acd058cd679a008619483d",
      "title": "إدارة الموارد البشرية (HRMS) | Bright AI - رواتب وأتمتة",
      "num": 10,
      "discovered": 1772933208653,
      "info": "404",
      "target_url": "https://brightai.site/interview",
      "source_url": "https://brightai.site/docs/solutions-hr"
    },
    {
      "page_id": "69acd058cd679a008619489f",
      "title": "Healthcare Solutions | Bright AI - Smart Medicine",
      "num": 10,
      "discovered": 1772933208653,
      "info": "404",
      "target_url": "https://brightai.site/interview",
      "source_url": "https://brightai.site/docs/solutions-healthcare-en"
    },
    {
      "page_id": "69acd058cd679a008619486d",
      "title": "حلول الرعاية الصحية | Bright AI - الطب المتصل والذكي",
      "num": 10,
      "discovered": 1772933208653,
      "info": "404",
      "target_url": "https://brightai.site/interview",
      "source_url": "https://brightai.site/docs/solutions-healthcare"
    },
    {
      "page_id": "69acd058cd679a008619489b",
      "title": "Fintech Solutions | Bright AI - Smart & Secure",
      "num": 10,
      "discovered": 1772933208653,
      "info": "404",
      "target_url": "https://brightai.site/interview",
      "source_url": "https://brightai.site/docs/solutions-finance-en"
    },
    {
      "page_id": "69acd058cd679a008619488c",
      "title": "حلول المالية (Fintech) | Bright AI - كشف الاحتيال والامتثال",
      "num": 11,
      "discovered": 1772933208653,
      "info": "404",
      "target_url": "https://brightai.site/interview",
      "source_url": "https://brightai.site/docs/solutions-finance"
    },
    {
      "page_id": "69acd058cd679a0086194873",
      "title": "Smart CRM Solutions | Bright AI - Know Your Customer",
      "num": 10,
      "discovered": 1772933208653,
      "info": "404",
      "target_url": "https://brightai.site/interview",
      "source_url": "https://brightai.site/docs/solutions-crm-en"
    },
    {
      "page_id": "69acd058cd679a008619484a",
      "title": "إدارة علاقات العملاء الذكية (CRM) | Bright AI",
      "num": 10,
      "discovered": 1772933208653,
      "info": "404",
      "target_url": "https://brightai.site/interview",
      "source_url": "https://brightai.site/docs/solutions-crm"
    },
    {
      "page_id": "69acd058cd679a0086194887",
      "title": "Business Intelligence (BI) | Bright AI",
      "num": 10,
      "discovered": 1772933208653,
      "info": "404",
      "target_url": "https://brightai.site/interview",
      "source_url": "https://brightai.site/docs/solutions-bi-en"
    },
    {
      "page_id": "69acd058cd679a008619485e",
      "title": "ذكاء الأعمال (BI) | Bright AI - لوحات تحكم تفاعلية",
      "num": 10,
      "discovered": 1772933208653,
      "info": "404",
      "target_url": "https://brightai.site/interview",
      "source_url": "https://brightai.site/docs/solutions-bi"
    },
    {
      "page_id": "69acd058cd679a0086194883",
      "title": "RPA Automation | Bright AI - Smart Work",
      "num": 11,
      "discovered": 1772933208653,
      "info": "404",
      "target_url": "https://brightai.site/interview",
      "source_url": "https://brightai.site/docs/smart-automation-en"
    },
    {
      "page_id": "69acd058cd679a00861948a9",
      "title": "أتمتة العمليات RPA | Bright AI - أتمتة ذكية للشركات",
      "num": 11,
      "discovered": 1772933208653,
      "info": "404",
      "target_url": "https://brightai.site/interview",
      "source_url": "https://brightai.site/docs/smart-automation"
    },
    {
      "page_id": "69acd058cd679a008619486b",
      "title": "Bright AI Services for Saudi Enterprises | AI Solutions &",
      "num": 13,
      "discovered": 1772933208653,
      "info": "404",
      "target_url": "https://brightai.site/interview",
      "source_url": "https://brightai.site/docs/services-overview-en"
    },
    {
      "page_id": "69acd058cd679a008619480c",
      "title": "خدمات Bright AI | حلول ذكاء اصطناعي متكاملة للشركات السعودية",
      "num": 13,
      "discovered": 1772933208653,
      "info": "404",
      "target_url": "https://brightai.site/interview",
      "source_url": "https://brightai.site/docs/services-overview"
    },
    {
      "page_id": "69acd058cd679a0086194886",
      "title": "Privacy Policy | Bright AI - How We Protect Your Data",
      "num": 10,
      "discovered": 1772933208653,
      "info": "404",
      "target_url": "https://brightai.site/interview",
      "source_url": "https://brightai.site/docs/privacy-policy-en"
    },
    {
      "page_id": "69acd058cd679a008619480a",
      "title": "سياسة الخصوصية | Bright AI - حماية بياناتك أولويتنا",
      "num": 10,
      "discovered": 1772933208653,
      "info": "404",
      "target_url": "https://brightai.site/interview",
      "source_url": "https://brightai.site/docs/privacy-policy"
    },
    {
      "page_id": "69acd058cd679a0086194868",
      "title": "Bright AI API Documentation - وثائق واجهة برمجة التطبيقات",
      "num": 10,
      "discovered": 1772933208653,
      "info": "404",
      "target_url": "https://brightai.site/interview",
      "source_url": "https://brightai.site/docs/openapi"
    },
    {
      "page_id": "69acd058cd679a00861948b1",
      "title": "FAQ | Bright AI - Got Questions? We Got Answers 💡",
      "num": 10,
      "discovered": 1772933208653,
      "info": "404",
      "target_url": "https://brightai.site/interview",
      "source_url": "https://brightai.site/docs/faq-en"
    },
    {
      "page_id": "69acd058cd679a008619485c",
      "title": "الأسئلة الشائعة | Bright AI - كل ما تحتاج معرفته",
      "num": 10,
      "discovered": 1772933208653,
      "info": "404",
      "target_url": "https://brightai.site/interview",
      "source_url": "https://brightai.site/docs/faq"
    },
    {
      "page_id": "69acd058cd679a008619480d",
      "title": "Data Analysis | Bright AI - Intelligence for Decision Making",
      "num": 11,
      "discovered": 1772933208653,
      "info": "404",
      "target_url": "https://brightai.site/interview",
      "source_url": "https://brightai.site/docs/data-analysis-en"
    },
    {
      "page_id": "69acd058cd679a0086194889",
      "title": "تحليل البيانات | Bright AI - ذكاء الأعمال والقرارات",
      "num": 11,
      "discovered": 1772933208653,
      "info": "404",
      "target_url": "https://brightai.site/interview",
      "source_url": "https://brightai.site/docs/data-analysis"
    },
    {
      "page_id": "69acd058cd679a00861948b2",
      "title": "Contact Us | Bright AI - Get in Touch",
      "num": 11,
      "discovered": 1772933208653,
      "info": "404",
      "target_url": "https://brightai.site/interview",
      "source_url": "https://brightai.site/docs/contact-en"
    },
    {
      "page_id": "69acd058cd679a0086194856",
      "title": "اتصل بنا | Bright AI - تواصل معنا اليوم",
      "num": 12,
      "discovered": 1772933208653,
      "info": "404",
      "target_url": "https://brightai.site/interview",
      "source_url": "https://brightai.site/docs/contact"
    },
    {
      "page_id": "69acd058cd679a0086194869",
      "title": "Tech Consultation | Bright AI السعودية",
      "num": 11,
      "discovered": 1772933208653,
      "info": "404",
      "target_url": "https://brightai.site/interview",
      "source_url": "https://brightai.site/docs/consultation-en"
    },
    {
      "page_id": "69acd058cd679a0086194885",
      "title": "استشارات تقنية | Bright AI - خارطة الطريق للتحول الرقمي",
      "num": 12,
      "discovered": 1772933208653,
      "info": "404",
      "target_url": "https://brightai.site/interview",
      "source_url": "https://brightai.site/docs/consultation"
    },
    {
      "page_id": "69acd058cd679a008619482b",
      "title": "Smart Chatbots | Bright AI - Arabic AI Assistants",
      "num": 10,
      "discovered": 1772933208653,
      "info": "404",
      "target_url": "https://brightai.site/interview",
      "source_url": "https://brightai.site/docs/ai-bots-en"
    },
    {
      "page_id": "69acd058cd679a00861948ae",
      "title": "روبوتات المحادثة الذكية | Bright AI - شات بوت عربي",
      "num": 10,
      "discovered": 1772933208653,
      "info": "404",
      "target_url": "https://brightai.site/interview",
      "source_url": "https://brightai.site/docs/ai-bots"
    },
    {
      "page_id": "69acd058cd679a0086194838",
      "title": "AIaaS - AI As A Service | Bright AI",
      "num": 11,
      "discovered": 1772933208653,
      "info": "404",
      "target_url": "https://brightai.site/interview",
      "source_url": "https://brightai.site/docs/ai-agent-en"
    },
    {
      "page_id": "69acd058cd679a0086194843",
      "title": "AIaaS - الذكاء الاصطناعي كخدمة | Bright AI",
      "num": 11,
      "discovered": 1772933208653,
      "info": "404",
      "target_url": "https://brightai.site/interview",
      "source_url": "https://brightai.site/docs/ai-agent"
    },
    {
      "page_id": "69acd058cd679a0086194839",
      "title": "مركز المستندات | Bright AI - دليلك الشامل للحلول الذكية",
      "num": 12,
      "discovered": 1772933208653,
      "info": "404",
      "target_url": "https://brightai.site/demo/resources/report-ai-saudi-2026",
      "source_url": "https://brightai.site/docs"
    },
    {
      "page_id": "69acd058cd679a0086194839",
      "title": "مركز المستندات | Bright AI - دليلك الشامل للحلول الذكية",
      "num": 10,
      "discovered": 1772933208653,
      "info": "404",
      "target_url": "https://brightai.site/job.MAISco",
      "source_url": "https://brightai.site/docs"
    },
    {
      "page_id": "69acd058cd679a0086194834",
      "title": "تحليل البيانات بـ AI | Bright AI",
      "num": 12,
      "discovered": 1772933208653,
      "info": "404",
      "target_url": "https://brightai.site/try/data-analyzer",
      "source_url": "https://brightai.site/data-analysis/"
    },
    {
      "page_id": "69acd058cd679a0086194834",
      "title": "تحليل البيانات بـ AI | Bright AI",
      "num": 14,
      "discovered": 1772933208653,
      "info": "404",
      "target_url": "https://brightai.site/demo/ocr-demo",
      "source_url": "https://brightai.site/data-analysis/"
    },
    {
      "page_id": "69acd058cd679a0086194834",
      "title": "تحليل البيانات بـ AI | Bright AI",
      "num": 15,
      "discovered": 1772933208653,
      "info": "404",
      "target_url": "https://brightai.site/demo/resources/report-ai-saudi-2026",
      "source_url": "https://brightai.site/data-analysis/"
    },
    {
      "page_id": "69acd058cd679a0086194815",
      "title": "تواصل معنا اليوم | Bright AI الرياض",
      "num": 13,
      "discovered": 1772933208653,
      "info": "404",
      "target_url": "https://brightai.site/interview",
      "source_url": "https://brightai.site/contact/"
    },
    {
      "page_id": "69acd058cd679a0086194833",
      "title": "استشارة ذكاء اصطناعي | Bright AI",
      "num": 11,
      "discovered": 1772933208653,
      "info": "404",
      "target_url": "https://brightai.site/interview",
      "source_url": "https://brightai.site/consultation/"
    },
    {
      "page_id": "69acd058cd679a0086194833",
      "title": "استشارة ذكاء اصطناعي | Bright AI",
      "num": 12,
      "discovered": 1772933208653,
      "info": "404",
      "target_url": "https://brightai.site/interview/Presentation",
      "source_url": "https://brightai.site/consultation/"
    },
    {
      "page_id": "69acd058cd679a0086194863",
      "title": "مدونة AI للشركات السعودية | Bright AI",
      "num": 16,
      "discovered": 1772933208653,
      "info": "404",
      "target_url": "https://brightai.site/demo/resources/report-ai-saudi-2026",
      "source_url": "https://brightai.site/blog/"
    },
    {
      "page_id": "69acd058cd679a0086194863",
      "title": "مدونة AI للشركات السعودية | Bright AI",
      "num": 15,
      "discovered": 1772933208653,
      "info": "404",
      "target_url": "https://brightai.site/job.MAISco",
      "source_url": "https://brightai.site/blog/"
    },
    {
      "page_id": "69acd058cd679a008619481b",
      "title": "روبوتات ذكاء اصطناعي متقدمة للشركات السعودية | Bright AI",
      "num": 13,
      "discovered": 1772933208653,
      "info": "404",
      "target_url": "https://brightai.site/job.MAISco",
      "source_url": "https://brightai.site/ai-bots/"
    },
    {
      "page_id": "69acd058cd679a008619481b",
      "title": "روبوتات ذكاء اصطناعي متقدمة للشركات السعودية | Bright AI",
      "num": 12,
      "discovered": 1772933208653,
      "info": "404",
      "target_url": "https://brightai.site/interview",
      "source_url": "https://brightai.site/ai-bots/"
    },
    {
      "page_id": "69acd058cd679a00861948b9",
      "title": "الذكاء الاصطناعي كخدمة (AIaaS) للشركات السعودية | Bright AI",
      "num": 15,
      "discovered": 1772933208653,
      "info": "404",
      "target_url": "https://brightai.site/demo",
      "source_url": "https://brightai.site/ai-agent/"
    },
    {
      "page_id": "69acd058cd679a00861948b9",
      "title": "الذكاء الاصطناعي كخدمة (AIaaS) للشركات السعودية | Bright AI",
      "num": 14,
      "discovered": 1772933208653,
      "info": "404",
      "target_url": "https://brightai.site/interview",
      "source_url": "https://brightai.site/ai-agent/"
    },
    {
      "page_id": "69acd058cd679a00861948c6",
      "title": "من نحن في Bright AI السعودية | خبرتنا",
      "num": 16,
      "discovered": 1772933208653,
      "info": "404",
      "target_url": "https://brightai.site/demo",
      "source_url": "https://brightai.site/about/"
    },
    {
      "page_id": "69acd058cd679a00861948c6",
      "title": "من نحن في Bright AI السعودية | خبرتنا",
      "num": 17,
      "discovered": 1772933208653,
      "info": "404",
      "target_url": "https://brightai.site/job.MAISco",
      "source_url": "https://brightai.site/about/"
    },
    {
      "page_id": "69acd058cd679a00861948b0",
      "title": "Bright AI | حلول ذكاء اصطناعي للشركات | شركة ذكاء اصطناعي في السعودية",
      "num": 18,
      "discovered": 1772933208653,
      "info": "404",
      "target_url": "https://brightai.site/try/data-quality",
      "source_url": "https://brightai.site/"
    },
    {
      "page_id": "69acd058cd679a00861948b0",
      "title": "Bright AI | حلول ذكاء اصطناعي للشركات | شركة ذكاء اصطناعي في السعودية",
      "num": 17,
      "discovered": 1772933208653,
      "info": "404",
      "target_url": "https://brightai.site/interview",
      "source_url": "https://brightai.site/"
    },
    {
      "page_id": "69acd058cd679a00861948b0",
      "title": "Bright AI | حلول ذكاء اصطناعي للشركات | شركة ذكاء اصطناعي في السعودية",
      "num": 16,
      "discovered": 1772933208653,
      "info": "404",
      "target_url": "https://brightai.site/try/data-analyzer",
      "source_url": "https://brightai.site/"
    },
    {
      "page_id": "69acd058cd679a00861948b0",
      "title": "Bright AI | حلول ذكاء اصطناعي للشركات | شركة ذكاء اصطناعي في السعودية",
      "num": 19,
      "discovered": 1772933208653,
      "info": "404",
      "target_url": "https://brightai.site/try/text-analysis",
      "source_url": "https://brightai.site/"
    }
  ],
  "issue_id": 8
}
